machomachomangler/__init__.py
machomachomangler/destruct.py
machomachomangler/macho.py
machomachomangler/macho_info.py
machomachomangler/pe.py
machomachomangler/pe_info.py
machomachomangler/util.py
machomachomangler/cmd/__init__.py
machomachomangler/cmd/redll.py
machomachomangler/tests/__init__.py
machomachomangler/tests/test_destruct.py
machomachomangler/tests/test_macho.py
machomachomangler/tests/test_redll.py
machomachomangler/tests/test_util.py
machomachomangler/tests/sample-dll/rebuild.py
machomachomangler/tests/sample-dll/i686/main.exe
machomachomangler/tests/sample-dll/i686/sample-dll.dll
machomachomangler/tests/sample-dll/src/main.c
machomachomangler/tests/sample-dll/src/sample-dll.c
machomachomangler/tests/sample-dll/x86_64/main.exe
machomachomangler/tests/sample-dll/x86_64/sample-dll.dll
machomachomangler/tests/sample-macho/build.py
machomachomangler/tests/sample-macho/fake-pymodule.c
machomachomangler/tests/sample-macho/main-dlopen.c
machomachomangler/tests/sample-macho/main-envvar.c
machomachomangler/tests/sample-macho/native-lib.c
machomachomangler-0.0.1.dist-info/DESCRIPTION.rst
machomachomangler-0.0.1.dist-info/METADATA
machomachomangler-0.0.1.dist-info/RECORD
machomachomangler-0.0.1.dist-info/WHEEL
machomachomangler-0.0.1.dist-info/metadata.json
machomachomangler-0.0.1.dist-info/top_level.txt
