Metadata-Version: 1.1
Name: machomachomangler
Version: 0.0.1
Summary: Tools for mangling Mach-O and PE binaries
Home-page: https://github.com/njsmith/machomachomangler
Author: Nathaniel J. Smith
Author-email: njs@pobox.com
License: MIT
Platform: UNKNOWN
Classifier: Development Status :: 3 - Alpha
Classifier: Intended Audience :: Developers
Classifier: License :: OSI Approved :: GNU Affero General Public License v3 or later (AGPLv3+)
Classifier: Programming Language :: Python :: 3.4
Classifier: Programming Language :: Python :: 3.5
Classifier: Operating System :: Microsoft
Classifier: Operating System :: MacOS :: MacOS X
Classifier: Topic :: Software Development :: Build Tools
Classifier: Topic :: Software Development :: Compilers
